falpy/__init__.py
falpy-0.0.1.dist-info/METADATA
falpy-0.0.1.dist-info/WHEEL
falpy-0.0.1.dist-info/top_level.txt
falpy-0.0.1.dist-info/RECORD
