Metadata-Version: 2.1
Name: falpy
Version: 0.0.1
Summary: Python binding for Falcie (A Federated Learning Framework)
Author-email: James Calo <jamesafcalo@gmail.com>
Classifier: Intended Audience :: Information Technology
Classifier: Intended Audience :: Science/Research
Classifier: License :: OSI Approved :: GNU General Public License v3 (GPLv3)
Classifier: Operating System :: OS Independent
Classifier: Programming Language :: Python :: 3.11
Classifier: Topic :: Scientific/Engineering :: Artificial Intelligence
Requires-Python: >=3.11
Requires-Dist: numpy
